README.md
setup.py
cc_dwh_streaming_pkg/__init__.py
cc_dwh_streaming_pkg/py_utils.py
cc_dwh_streaming_pkg/spark_utils.py
cc_dwh_streaming_pkg.egg-info/PKG-INFO
cc_dwh_streaming_pkg.egg-info/SOURCES.txt
cc_dwh_streaming_pkg.egg-info/dependency_links.txt
cc_dwh_streaming_pkg.egg-info/requires.txt
cc_dwh_streaming_pkg.egg-info/top_level.txt