Metadata-Version: 2.1
Name: cc-dwh-streaming-pkg
Version: 1.0.2
Summary: serving CC dwh streaming apps
Home-page: UNKNOWN
Author: Asaf Shelach
License: UNKNOWN
Platform: UNKNOWN
